<?xml version="1.0" encoding="utf-8" ?>
<dwsync>
<file name="header.php" server="D:/wamp/www/whales/" local="131012803218327714" remote="131012803210000000" Dst="1" />
<file name="head.php" server="D:/wamp/www/whales/" local="131012796674661959" remote="131012796670000000" Dst="1" />
<file name="footer.php" server="D:/wamp/www/whales/" local="131011905174538028" remote="131011905170000000" Dst="1" />
<file name="footer.php" server="C:/wamp/www/whales/" local="131027822701226656" remote="131027822700000000" Dst="2" />
<file name="head.php" server="C:/wamp/www/whales/" local="131027183607326634" remote="131027183600000000" Dst="2" />
<file name="header.php" server="C:/wamp/www/whales/" local="131027822254838794" remote="131027822250000000" Dst="2" />
<file name="header.php" server="D:/wamp64/www/whales/" local="131028260295565121" remote="131028260290000000" Dst="2" />
<file name="head.php" server="D:/wamp64/www/whales/" local="131027183600000000" remote="131027183600000000" Dst="2" />
<file name="footer.php" server="D:/wamp64/www/whales/" local="131027864026912157" remote="131027864020000000" Dst="2" />
</dwsync>